dispatchsdk/__init__.py
dispatchsdk/client.py
dispatchsdk/connector.py
dispatchsdk/errors.py
dispatchsdk/hmac.py
dispatchsdk-0.1.4.dist-info/DESCRIPTION.rst
dispatchsdk-0.1.4.dist-info/METADATA
dispatchsdk-0.1.4.dist-info/RECORD
dispatchsdk-0.1.4.dist-info/WHEEL
dispatchsdk-0.1.4.dist-info/metadata.json
dispatchsdk-0.1.4.dist-info/top_level.txt
