Metadata-Version: 2.0
Name: dispatchsdk
Version: 0.1.4
Summary: SDK for interacting with the Dispatch platform
Home-page: https://github.com/DispatchMe/python-sdk
Author: Jason Raede
Author-email: jason@dispatch.me
License: MIT
Platform: ANY
Requires: requests
Requires: urllib3
Requires-Python: >=3
